setup.cfg
setup.py
chuk/__init__.py
chuk/bitfield.py
chuk/clock.py
chuk.egg-info/PKG-INFO
chuk.egg-info/SOURCES.txt
chuk.egg-info/dependency_links.txt
chuk.egg-info/requires.txt
chuk.egg-info/top_level.txt
chuk/Application/ConfigDir.py
chuk/Application/ConfigReader.py
chuk/Application/ConnChoice.py
chuk/Application/CreateIcons.py
chuk/Application/GUI.py
chuk/Application/NumberFormats.py
chuk/Application/PeerID.py
chuk/Application/__init__.py
chuk/Application/inifile.py
chuk/Application/makemetafile.py
chuk/Application/parseargs.py
chuk/Application/parsedir.py
chuk/Application/reannounce.py
chuk/Client/Choker.py
chuk/Client/Connecter.py
chuk/Client/CurrentRateMeasure.py
chuk/Client/Downloader.py
chuk/Client/DownloaderFeedback.py
chuk/Client/HTTPDownloader.py
chuk/Client/PiecePicker.py
chuk/Client/RateLimiter.py
chuk/Client/RateMeasure.py
chuk/Client/Rerequester.py
chuk/Client/Statistics.py
chuk/Client/Uploader.py
chuk/Client/__init__.py
chuk/Client/download_bt1.py
chuk/Client/launchmanycore.py
chuk/Download/__init__.py
chuk/Download/depend.py
chuk/Download/main.py
chuk/Meta/BTTree.py
chuk/Meta/Info.py
chuk/Meta/__init__.py
chuk/Meta/bencode.py
chuk/Network/BTcrypto.py
chuk/Network/Encrypter.py
chuk/Network/NatCheck.py
chuk/Network/NetworkAddress.py
chuk/Network/RawServer.py
chuk/Network/ServerPortHandler.py
chuk/Network/SocketHandler.py
chuk/Network/__init__.py
chuk/Network/natpunch.py
chuk/Network/selectpoll.py
chuk/Network/zurllib.py
chuk/Storage/FileSelector.py
chuk/Storage/PieceBuffer.py
chuk/Storage/Storage.py
chuk/Storage/StorageWrapper.py
chuk/Storage/__init__.py
chuk/Tracker/Filter.py
chuk/Tracker/HTTPHandler.py
chuk/Tracker/T2T.py
chuk/Tracker/__init__.py
chuk/Tracker/torrentlistparse.py
chuk/Tracker/track.py