Metadata-Version: 1.0
Name: chuk
Version: 0.4.0
Summary: John Hoffman's fork of the original bittorrent
Home-page: UNKNOWN
Author: Chris Markiewicz, Bram Cohen, John Hoffman, Uoti Arpala et. al.
Author-email: <effigies@gmail.com>
License: MIT
Platform: UNKNOWN
